MANIFEST.in
README.rst
setup.py
myls/__init__.py
myls/utils.py
myls.egg-info/PKG-INFO
myls.egg-info/SOURCES.txt
myls.egg-info/dependency_links.txt
myls.egg-info/entry_points.txt
myls.egg-info/requires.txt
myls.egg-info/top_level.txt