Metadata-Version: 1.1
Name: myls
Version: 0.0.1
Summary: UNIX command ls python wrapper
Home-page: https://github.com/chkumar/myls.git
Author: Chandan Kumar
Author-email: chandankumar.093047@gmail.com
License: GPL
Keywords: sample python ls development
Platform: UNKNOWN
Classifier: Development Status :: 3 - Alpha
Classifier: Intended Audience :: Developers
Classifier: Topic :: Software Development :: Build Tools
Classifier: License :: OSI Approved :: MIT License
Classifier: Programming Language :: Python :: 2
Classifier: Programming Language :: Python :: 2.6
Classifier: Programming Language :: Python :: 2.7
Classifier: Programming Language :: Python :: 3
Classifier: Programming Language :: Python :: 3.2
Classifier: Programming Language :: Python :: 3.3
Classifier: Programming Language :: Python :: 3.4
